index.py
semanticsearch-0.0.1.dist-info/METADATA
semanticsearch-0.0.1.dist-info/WHEEL
semanticsearch-0.0.1.dist-info/top_level.txt
semanticsearch-0.0.1.dist-info/RECORD
