Metadata-Version: 2.1
Name: semanticsearch
Version: 0.0.1
Summary: Semantic search powered by git commit messages
Home-page: UNKNOWN
Author: UNKNOWN
Author-email: UNKNOWN
License: UNKNOWN
Platform: UNKNOWN
